tinysoundfont-0.3.7.dist-info/WHEEL
tinysoundfont-0.3.7.dist-info/METADATA
tinysoundfont-0.3.7.dist-info/RECORD
tinysoundfont-0.3.7.dist-info/licenses/NOTICE
tinysoundfont-0.3.7.dist-info/licenses/LICENSE
tinysoundfont.libs/libstdc++-8baf04f9.so.6.0.28
tinysoundfont.libs/libgcc_s-8b50eaaa.so.1
tinysoundfont/sequencer.py
tinysoundfont/_tinysoundfont.cpython-39-i386-linux-gnu.so
tinysoundfont/__init__.py
tinysoundfont/__main__.py
tinysoundfont/synth.py
tinysoundfont/midi/__init__.py
